vyte/__init__.py
vyte/__version__.py
vyte/exceptions.py
vyte/cli/__init__.py
vyte/cli/commands.py
vyte/cli/display.py
vyte/cli/interactive.py
vyte/core/__init__.py
vyte/core/alembic_setup.py
vyte/core/config.py
vyte/core/dependencies.py
vyte/core/generator.py
vyte/core/renderer.py
vyte/strategies/__init.py
vyte/strategies/base.py
vyte/strategies/django_rest.py
vyte/strategies/fastapi.py
vyte/strategies/flask_restx.py
vyte/templates/common/.dockerignore.j2
vyte/templates/common/.gitignore.j2
vyte/templates/common/Dockerfile.j2
vyte/templates/common/LICENSE.j2
vyte/templates/common/README.md.j2
vyte/templates/common/docker-compose.yml.j2
vyte/templates/common/env.example.j2
vyte/templates/common/pyproject.toml.j2
vyte/templates/common/pytest.ini.j2
vyte/templates/common/security.py.j2
vyte/templates/common/test_security.py.j2
vyte/templates/django-rest/djangoORM/.env.test.example.j2
vyte/templates/django-rest/djangoORM/conftest.py.j2
vyte/templates/django-rest/djangoORM/models.py.j2
vyte/templates/django-rest/djangoORM/permissions.py.j2
vyte/templates/django-rest/djangoORM/pytest.ini.j2
vyte/templates/django-rest/djangoORM/serializers.py.j2
vyte/templates/django-rest/djangoORM/settings.py.j2
vyte/templates/django-rest/djangoORM/test_api.py.j2
vyte/templates/django-rest/djangoORM/test_models.py.j2
vyte/templates/django-rest/djangoORM/urls.py.j2
vyte/templates/django-rest/djangoORM/views.py.j2
vyte/templates/fastapi/sqlalchemy/.env.test.example.j2
vyte/templates/fastapi/sqlalchemy/config.py.j2
vyte/templates/fastapi/sqlalchemy/conftest.py.j2
vyte/templates/fastapi/sqlalchemy/database.py.j2
vyte/templates/fastapi/sqlalchemy/main.py.j2
vyte/templates/fastapi/sqlalchemy/models.py.j2
vyte/templates/fastapi/sqlalchemy/pytest.ini.j2
vyte/templates/fastapi/sqlalchemy/routes.py.j2
vyte/templates/fastapi/sqlalchemy/schemas.py.j2
vyte/templates/fastapi/sqlalchemy/test_api.py.j2
vyte/templates/fastapi/sqlalchemy/test_models.py.j2
vyte-2.0.5.dist-info/licenses/LICENSE
vyte-2.0.5.dist-info/METADATA
vyte-2.0.5.dist-info/WHEEL
vyte-2.0.5.dist-info/entry_points.txt
vyte-2.0.5.dist-info/top_level.txt
vyte-2.0.5.dist-info/RECORD
