Metadata-Version: 2.4
Name: vyte
Version: 2.0.5
Summary: Professional API project generator for Python - Flask, FastAPI, Django-Rest
Author-email: PabloDomi <Domi@usal.es>
License-Expression: MIT
Project-URL: Homepage, https://github.com/PabloDomi/Vyte
Project-URL: Bug Tracker, https://github.com/PabloDomi/Vyte/issues
Project-URL: Documentation, https://github.com/PabloDomi/Vyte/blob/main/docs/
Project-URL: Changelog, https://github.com/PabloDomi/Vyte/blob/main/docs/CHANGELOG.md
Project-URL: Source Code, https://github.com/PabloDomi/Vyte
Project-URL: Logo, https://raw.githubusercontent.com/PabloDomi/Vyte/main/images/Logo_V_Transparente.png
Keywords: api,generator,flask,fastapi,django,scaffolding,boilerplate
Classifier: Development Status :: 4 - Beta
Classifier: Intended Audience :: Developers
Classifier: Programming Language :: Python :: 3
Classifier: Programming Language :: Python :: 3.11
Classifier: Programming Language :: Python :: 3.12
Classifier: Programming Language :: Python :: 3.13
Classifier: Topic :: Software Development :: Code Generators
Classifier: Topic :: Software Development :: Libraries :: Application Frameworks
Requires-Python: <3.14,>=3.11
License-File: LICENSE
Requires-Dist: click>=8.1.7
Requires-Dist: jinja2>=3.1.2
Requires-Dist: pydantic>=2.5.0
Requires-Dist: pydantic-settings>=2.1.0
Requires-Dist: rich>=13.7.0
Requires-Dist: inquirerpy>=0.3.4
Requires-Dist: colorama>=0.4.6
Provides-Extra: dev
Requires-Dist: pytest>=7.4.3; extra == "dev"
Requires-Dist: pytest-cov>=4.1.0; extra == "dev"
Requires-Dist: pytest-asyncio>=0.21.0; extra == "dev"
Requires-Dist: pytest-timeout>=2.1.0; extra == "dev"
Requires-Dist: fastapi>=0.104.0; extra == "dev"
Requires-Dist: flask-restx>=1.2.0; extra == "dev"
Requires-Dist: flask>=3.0.0; extra == "dev"
Requires-Dist: uvicorn[standard]>=0.24.0; extra == "dev"
Requires-Dist: sqlalchemy>=2.0.0; extra == "dev"
Requires-Dist: tortoise-orm>=0.20.0; extra == "dev"
Requires-Dist: peewee>=3.17.0; extra == "dev"
Requires-Dist: psycopg2-binary>=2.9.9; extra == "dev"
Requires-Dist: asyncpg>=0.29.0; extra == "dev"
Requires-Dist: httpx>=0.25.0; extra == "dev"
Requires-Dist: anyio>=4.0.0; extra == "dev"
Provides-Extra: docs
Requires-Dist: mkdocs>=1.5.0; extra == "docs"
Requires-Dist: mkdocs-material>=9.5.0; extra == "docs"
Requires-Dist: mkdocstrings[python]>=0.24.0; extra == "docs"
Requires-Dist: mkdocs-git-revision-date-localized-plugin>=1.2.0; extra == "docs"
Dynamic: license-file
